Workbook

Sheet LisezMoi
A1: Iron Front — Tableur d'équilibrage économique v0.1
A3: Formules dérivées d'OGame (wikis owiki.de / Fandom, clones open source pr0game, 2Moons, alaingilbert/ogame),
A4: transposées dans l'univers Iron Front (voir design/docs/univers-du-jeu.md).
A6: CODE COULEUR :
A7: • Texte BLEU sur fond JAUNE = paramètre modifiable (levier d'équilibrage) — tout recalcule.
A8: • Texte NOIR = formule, ne pas modifier à la main.
A10: FEUILLES :
A11: • Parametres — leviers globaux (vitesses, % épaves, pillage, taux d'échange…)
A12: • Mines — production/coûts/amortissement niveaux 1-40 des 3 mines + centrale + dépôts
A13: • Batiments — coûts des bâtiments de support (niveau N au choix)
A14: • Recherches — coûts des technologies (niveau N au choix)
A15: • Unites — stats et coûts des 14 unités + valeur d'épaves + points d'expédition
... A23: • Rapid fire : valeurs OGame v7 indicatives, à ajuster en playtest.

Sheet Parametres
A1: Paramètres globaux (leviers d'équilibrage)
A3: Paramètre | B3: Valeur | C3: Note
A4: Vitesse économie (×) | B4: 4 | C4: OGame classique = 1 ; mobile moderne = 4-8
A5: Vitesse des convois (×) | B5: 2 | C5: Multiplie les vitesses, divise les temps de vol
A6: Vitesse recherche (×) | B6: 4
A7: % épaves (véhicules détruits → champ d'épaves) | B7: 0.3 | C7: OGame : 30 %
A8: Pillage joueurs actifs | B8: 0.5 | C8: 50 % des ressources posées
A9: Pillage inactifs | B9: 0.75 | C9: Décision actée : 75 % pour tous
A10: Valeur d'échange : Acier | B10: 1 | C10: Ratio 3:2:1
A11: Valeur d'échange : Composants | B11: 1.5
A12: Valeur d'échange : Carburant | B12: 3
A13: Facteur biome raffinerie (défaut) | B13: 1.2 | C13: Toundra ≈ 1,36 ; plaines ≈ 1,2 ; désert ≈ 1,05
A14: Prod. de base gratuite Acier (/h, ×vitesse) | B14: 30
A15: Prod. de base gratuite Composants (/h, ×vitesse) | B15: 15
A16: Énergie par Générateur d'appoint | B16: 33 | C16: OGame : (Tmax+140)/6, moyenne ≈ 33
A17: Fret du Drone de reconnaissance | B17: 10 | C17: Décision actée
A18: Limite de bash (attaques/base/24 h) | B18: 6
A19: Épaves pour 1 % de chance de bunker | B19: 100000
A20: Chance max de bunker | B20: 0.2 | C20: Atteinte à 2 M d'épaves
A21: Diviseur temps de construction bâtiments | B21: 2500 | C21: t(h)=(S+C)/(div×(1+Génie)×vitesse×2^Chantier)
A22: Diviseur temps de recherche | B22: 1000 | C22: t(h)=(S+C)/(div×(1+Labo))/vitesse recherche

Sheet Mines
A1: Mines & énergie — niveaux 1 à 40
A2: Prod/h = coef × L × 1,1^L × vitesse éco (raffinerie : × facteur biome). Coût niv L = base × facteur^(L-1). Amort. = coût éq.acier ÷ Δprod éq.acier ÷ 24.
A3: MINE D'ACIER (Steel Mine) | I3: ATELIER DE COMPOSANTS (Component W.) | Q3: RAFFINERIE DE CARBURANT (Fuel Ref.) | Y3: CENTRALE ÉLECTRIQUE (Power Plant) | AD3: DÉPÔT DE STOCKAGE (acier — comp. : coût ×1,5)
A4: Niveau | B4: Prod/h | C4: ΔProd/h | D4: Énergie | E4: Coût Acier | F4: Coût Comp. | G4: Amort. (j) | I4: Niveau | J4: Prod/h | K4: ΔProd/h | L4: Énergie | M4: Coût Acier | N4: Coût Comp. | O4: Amort. (j) | Q4: Niveau | R4: Prod/h | S4: ΔProd/h | T4: Énergie | U4: Coût Acier | V4: Coût Comp. | W4: Amort. (j) | Y4: Niveau | Z4: Énergie | AA4: Coût Acier | AB4: Coût Comp. | AD4: Niveau | AE4: Capacité | AF4: Coût Acier
A5: 1 | B5: =ROUND(30*A5*POWER(1.1,A5)*Parametres!$B$4,0) -> 132 | C5: =B5-ROUND(30*(A5-1)*POWER(1.1,A5-1)*Parametres!$B$4,0) -> 132 | D5: =ROUND(10*A5*POWER(1.1,A5),0) -> 11 | E5: =ROUND(60*POWER(1.5,A5-1),0) -> 60 | F5: =ROUND(15*POWER(1.5,A5-1),0) -> 15 | G5: =(E5*Parametres!$B$10+F5*Parametres!$B$11)/(C5*Parametres!$B$10)/24 -> 0.026041667 | I5: 1 | J5: =ROUND(20*I5*POWER(1.1,I5)*Parametres!$B$4,0) -> 88 | K5: =J5-ROUND(20*(I5-1)*POWER(1.1,I5-1)*Parametres!$B$4,0) -> 88 | L5: =ROUND(10*I5*POWER(1.1,I5),0) -> 11 | M5: =ROUND(48*POWER(1.6,I5-1),0) -> 48 | N5: =ROUND(24*POWER(1.6,I5-1),0) -> 24 | O5: =(M5*Parametres!$B$10+N5*Parametres!$B$11)/(K5*Parametres!$B$11)/24 -> 0.026515152 | Q5: 1 | R5: =ROUND(10*Q5*POWER(1.1,Q5)*Parametres!$B$4*Parametres!$B$13,0) -> 53 | S5: =R5-ROUND(10*(Q5-1)*POWER(1.1,Q5-1)*Parametres!$B$4*Parametres!$B$13,0) -> 53 | T5: =ROUND(20*Q5*POWER(1.1,Q5),0) -> 22 | U5: =ROUND(225*POWER(1.5,Q5-1),0) -> 225 | V5: =ROUND(75*POWER(1.5,Q5-1),0) -> 75 | W5: =(U5*Parametres!$B$10+V5*Parametres!$B$11)/(S5*Parametres!$B$12)/24 -> 0.088443396 | Y5: 1 | Z5: =ROUND(20*Y5*POWER(1.1,Y5),0) -> 22 | AA5: =ROUND(75*POWER(1.5,Y5-1),0) -> 75 | AB5: =ROUND(30*POWER(1.5,Y5-1),0) -> 30 | AD5: 1 | AE5: =5000*FLOOR(2.5*EXP(20*AD5/33),1) -> 20000 | AF5: =1000*POWER(2,AD5-1) -> 1000
A6: 2 | B6: =ROUND(30*A6*POWER(1.1,A6)*Parametres!$B$4,0) -> 290 | C6: =B6-ROUND(30*(A6-1)*POWER(1.1,A6-1)*Parametres!$B$4,0) -> 158 | D6: =ROUND(10*A6*POWER(1.1,A6),0) -> 24 | E6: =ROUND(60*POWER(1.5,A6-1),0) -> 90 | F6: =ROUND(15*POWER(1.5,A6-1),0) -> 23 | G6: =(E6*Parametres!$B$10+F6*Parametres!$B$11)/(C6*Parametres!$B$10)/24 -> 0.032832278 | I6: 2 | J6: =ROUND(20*I6*POWER(1.1,I6)*Parametres!$B$4,0) -> 194 | K6: =J6-ROUND(20*(I6-1)*POWER(1.1,I6-1)*Parametres!$B$4,0) -> 106 | L6: =ROUND(10*I6*POWER(1.1,I6),0) -> 24 | M6: =ROUND(48*POWER(1.6,I6-1),0) -> 77 | N6: =ROUND(24*POWER(1.6,I6-1),0) -> 38 | O6: =(M6*Parametres!$B$10+N6*Parametres!$B$11)/(K6*Parametres!$B$11)/24 -> 0.035115304 | Q6: 2 | R6: =ROUND(10*Q6*POWER(1.1,Q6)*Parametres!$B$4*Parametres!$B$13,0) -> 116 | S6: =R6-ROUND(10*(Q6-1)*POWER(1.1,Q6-1)*Parametres!$B$4*Parametres!$B$13,0) -> 63 | T6: =ROUND(20*Q6*POWER(1.1,Q6),0) -> 48 | U6: =ROUND(225*POWER(1.5,Q6-1),0) -> 338 | V6: =ROUND(75*POWER(1.5,Q6-1),0) -> 113 | W6: =(U6*Parametres!$B$10+V6*Parametres!$B$11)/(S6*Parametres!$B$12)/24 -> 0.11188272 | Y6: 2 | Z6: =ROUND(20*Y6*POWER(1.1,Y6),0) -> 48 | AA6: =ROUND(75*POWER(1.5,Y6-1),0) -> 113 | AB6: =ROUND(30*POWER(1.5,Y6-1),0) -> 45 | AD6: 2 | AE6: =5000*FLOOR(2.5*EXP(20*AD6/33),1) -> 40000 | AF6: =1000*POWER(2,AD6-1) -> 2000
A7: 3 | B7: =ROUND(30*A7*POWER(1.1,A7)*Parametres!$B$4,0) -> 479 | C7: =B7-ROUND(30*(A7-1)*POWER(1.1,A7-1)*Parametres!$B$4,0) -> 189 | D7: =ROUND(10*A7*POWER(1.1,A7),0) -> 40 | E7: =ROUND(60*POWER(1.5,A7-1),0) -> 135 | F7: =ROUND(15*POWER(1.5,A7-1),0) -> 34 | G7: =(E7*Parametres!$B$10+F7*Parametres!$B$11)/(C7*Parametres!$B$10)/24 -> 0.041005291 | I7: 3 | J7: =ROUND(20*I7*POWER(1.1,I7)*Parametres!$B$4,0) -> 319 | K7: =J7-ROUND(20*(I7-1)*POWER(1.1,I7-1)*Parametres!$B$4,0) -> 125 | L7: =ROUND(10*I7*POWER(1.1,I7),0) -> 40 | M7: =ROUND(48*POWER(1.6,I7-1),0) -> 123 | N7: =ROUND(24*POWER(1.6,I7-1),0) -> 61 | O7: =(M7*Parametres!$B$10+N7*Parametres!$B$11)/(K7*Parametres!$B$11)/24 -> 0.047666667 | Q7: 3 | R7: =ROUND(10*Q7*POWER(1.1,Q7)*Parametres!$B$4*Parametres!$B$13,0) -> 192 | S7: =R7-ROUND(10*(Q7-1)*POWER(1.1,Q7-1)*Parametres!$B$4*Parametres!$B$13,0) -> 76 | T7: =ROUND(20*Q7*POWER(1.1,Q7),0) -> 80 | U7: =ROUND(225*POWER(1.5,Q7-1),0) -> 506 | V7: =ROUND(75*POWER(1.5,Q7-1),0) -> 169 | W7: =(U7*Parametres!$B$10+V7*Parametres!$B$11)/(S7*Parametres!$B$12)/24 -> 0.13879751 | Y7: 3 | Z7: =ROUND(20*Y7*POWER(1.1,Y7),0) -> 80 | AA7: =ROUND(75*POWER(1.5,Y7-1),0) -> 169 | AB7: =ROUND(30*POWER(1.5,Y7-1),0) -> 68 | AD7: 3 | AE7: =5000*FLOOR(2.5*EXP(20*AD7/33),1) -> 75000 | AF7: =1000*POWER(2,AD7-1) -> 4000
A8: 4 | B8: =ROUND(30*A8*POWER(1.1,A8)*Parametres!$B$4,0) -> 703 | C8: =B8-ROUND(30*(A8-1)*POWER(1.1,A8-1)*Parametres!$B$4,0) -> 224 | D8: =ROUND(10*A8*POWER(1.1,A8),0) -> 59 | E8: =ROUND(60*POWER(1.5,A8-1),0) -> 203 | F8: =ROUND(15*POWER(1.5,A8-1),0) -> 51 | G8: =(E8*Parametres!$B$10+F8*Parametres!$B$11)/(C8*Parametres!$B$10)/24 -> 0.051990327 | I8: 4 | J8: =ROUND(20*I8*POWER(1.1,I8)*Parametres!$B$4,0) -> 469 | K8: =J8-ROUND(20*(I8-1)*POWER(1.1,I8-1)*Parametres!$B$4,0) -> 150 | L8: =ROUND(10*I8*POWER(1.1,I8),0) -> 59 | M8: =ROUND(48*POWER(1.6,I8-1),0) -> 197 | N8: =ROUND(24*POWER(1.6,I8-1),0) -> 98 | O8: =(M8*Parametres!$B$10+N8*Parametres!$B$11)/(K8*Parametres!$B$11)/24 -> 0.063703704 | Q8: 4 | R8: =ROUND(10*Q8*POWER(1.1,Q8)*Parametres!$B$4*Parametres!$B$13,0) -> 281 | S8: =R8-ROUND(10*(Q8-1)*POWER(1.1,Q8-1)*Parametres!$B$4*Parametres!$B$13,0) -> 89 | T8: =ROUND(20*Q8*POWER(1.1,Q8),0) -> 117 | U8: =ROUND(225*POWER(1.5,Q8-1),0) -> 759 | V8: =ROUND(75*POWER(1.5,Q8-1),0) -> 253 | W8: =(U8*Parametres!$B$10+V8*Parametres!$B$11)/(S8*Parametres!$B$12)/24 -> 0.17766854 | Y8: 4 | Z8: =ROUND(20*Y8*POWER(1.1,Y8),0) -> 117 | AA8: =ROUND(75*POWER(1.5,Y8-1),0) -> 253 | AB8: =ROUND(30*POWER(1.5,Y8-1),0) -> 101 | AD8: 4 | AE8: =5000*FLOOR(2.5*EXP(20*AD8/33),1) -> 140000 | AF8: =1000*POWER(2,AD8-1) -> 8000
A9: 5 | B9: =ROUND(30*A9*POWER(1.1,A9)*Parametres!$B$4,0) -> 966 | C9: =B9-ROUND(30*(A9-1)*POWER(1.1,A9-1)*Parametres!$B$4,0) -> 263 | D9: =ROUND(10*A9*POWER(1.1,A9),0) -> 81 | E9: =ROUND(60*POWER(1.5,A9-1),0) -> 304 | F9: =ROUND(15*POWER(1.5,A9-1),0) -> 76 | G9: =(E9*Parametres!$B$10+F9*Parametres!$B$11)/(C9*Parametres!$B$10)/24 -> 0.066223067 | I9: 5 | J9: =ROUND(20*I9*POWER(1.1,I9)*Parametres!$B$4,0) -> 644 | K9: =J9-ROUND(20*(I9-1)*POWER(1.1,I9-1)*Parametres!$B$4,0) -> 175 | L9: =ROUND(10*I9*POWER(1.1,I9),0) -> 81 | M9: =ROUND(48*POWER(1.6,I9-1),0) -> 315 | N9: =ROUND(24*POWER(1.6,I9-1),0) -> 157 | O9: =(M9*Parametres!$B$10+N9*Parametres!$B$11)/(K9*Parametres!$B$11)/24 -> 0.087380952 | Q9: 5 | R9: =ROUND(10*Q9*POWER(1.1,Q9)*Parametres!$B$4*Parametres!$B$13,0) -> 387 | S9: =R9-ROUND(10*(Q9-1)*POWER(1.1,Q9-1)*Parametres!$B$4*Parametres!$B$13,0) -> 106 | T9: =ROUND(20*Q9*POWER(1.1,Q9),0) -> 161 | U9: =ROUND(225*POWER(1.5,Q9-1),0) -> 1139 | V9: =ROUND(75*POWER(1.5,Q9-1),0) -> 380 | W9: =(U9*Parametres!$B$10+V9*Parametres!$B$11)/(S9*Parametres!$B$12)/24 -> 0.22392558 | Y9: 5 | Z9: =ROUND(20*Y9*POWER(1.1,Y9),0) -> 161 | AA9: =ROUND(75*POWER(1.5,Y9-1),0) -> 380 | AB9: =ROUND(30*POWER(1.5,Y9-1),0) -> 152 | AD9: 5 | AE9: =5000*FLOOR(2.5*EXP(20*AD9/33),1) -> 255000 | AF9: =1000*POWER(2,AD9-1) -> 16000
A10: 6 | B10: =ROUND(30*A10*POWER(1.1,A10)*Parametres!$B$4,0) -> 1276 | C10: =B10-ROUND(30*(A10-1)*POWER(1.1,A10-1)*Parametres!$B$4,0) -> 310 | D10: =ROUND(10*A10*POWER(1.1,A10),0) -> 106 | E10: =ROUND(60*POWER(1.5,A10-1),0) -> 456 | F10: =ROUND(15*POWER(1.5,A10-1),0) -> 114 | G10: =(E10*Parametres!$B$10+F10*Parametres!$B$11)/(C10*Parametres!$B$10)/24 -> 0.084274194 | I10: 6 | J10: =ROUND(20*I10*POWER(1.1,I10)*Parametres!$B$4,0) -> 850 | K10: =J10-ROUND(20*(I10-1)*POWER(1.1,I10-1)*Parametres!$B$4,0) -> 206 | L10: =ROUND(10*I10*POWER(1.1,I10),0) -> 106 | M10: =ROUND(48*POWER(1.6,I10-1),0) -> 503 | N10: =ROUND(24*POWER(1.6,I10-1),0) -> 252 | O10: =(M10*Parametres!$B$10+N10*Parametres!$B$11)/(K10*Parametres!$B$11)/24 -> 0.1187972 | Q10: 6 | R10: =ROUND(10*Q10*POWER(1.1,Q10)*Parametres!$B$4*Parametres!$B$13,0) -> 510 | S10: =R10-ROUND(10*(Q10-1)*POWER(1.1,Q10-1)*Parametres!$B$4*Parametres!$B$13,0) -> 123 | T10: =ROUND(20*Q10*POWER(1.1,Q10),0) -> 213 | U10: =ROUND(225*POWER(1.5,Q10-1),0) -> 1709 | V10: =ROUND(75*POWER(1.5,Q10-1),0) -> 570 | W10: =(U10*Parametres!$B$10+V10*Parametres!$B$11)/(S10*Parametres!$B$12)/24 -> 0.28952123 | Y10: 6 | Z10: =ROUND(20*Y10*POWER(1.1,Y10),0) -> 213 | AA10: =ROUND(75*POWER(1.5,Y10-1),0) -> 570 | AB10: =ROUND(30*POWER(1.5,Y10-1),0) -> 228 | AD10: 6 | AE10: =5000*FLOOR(2.5*EXP(20*AD10/33),1) -> 470000 | AF10: =1000*POWER(2,AD10-1) -> 32000
A11: 7 | B11: =ROUND(30*A11*POWER(1.1,A11)*Parametres!$B$4,0) -> 1637 | C11: =B11-ROUND(30*(A11-1)*POWER(1.1,A11-1)*Parametres!$B$4,0) -> 361 | D11: =ROUND(10*A11*POWER(1.1,A11),0) -> 136 | E11: =ROUND(60*POWER(1.5,A11-1),0) -> 683 | F11: =ROUND(15*POWER(1.5,A11-1),0) -> 171 | G11: =(E11*Parametres!$B$10+F11*Parametres!$B$11)/(C11*Parametres!$B$10)/24 -> 0.10843721 | I11: 7 | J11: =ROUND(20*I11*POWER(1.1,I11)*Parametres!$B$4,0) -> 1091 | K11: =J11-ROUND(20*(I11-1)*POWER(1.1,I11-1)*Parametres!$B$4,0) -> 241 | L11: =ROUND(10*I11*POWER(1.1,I11),0) -> 136 | M11: =ROUND(48*POWER(1.6,I11-1),0) -> 805 | N11: =ROUND(24*POWER(1.6,I11-1),0) -> 403 | O11: =(M11*Parametres!$B$10+N11*Parametres!$B$11)/(K11*Parametres!$B$11)/24 -> 0.16245966 | Q11: 7 | R11: =ROUND(10*Q11*POWER(1.1,Q11)*Parametres!$B$4*Parametres!$B$13,0) -> 655 | S11: =R11-ROUND(10*(Q11-1)*POWER(1.1,Q11-1)*Parametres!$B$4*Parametres!$B$13,0) -> 145 | T11: =ROUND(20*Q11*POWER(1.1,Q11),0) -> 273 | U11: =ROUND(225*POWER(1.5,Q11-1),0) -> 2563 | V11: =ROUND(75*POWER(1.5,Q11-1),0) -> 854 | W11: =(U11*Parametres!$B$10+V11*Parametres!$B$11)/(S11*Parametres!$B$12)/24 -> 0.36819923 | Y11: 7 | Z11: =ROUND(20*Y11*POWER(1.1,Y11),0) -> 273 | AA11: =ROUND(75*POWER(1.5,Y11-1),0) -> 854 | AB11: =ROUND(30*POWER(1.5,Y11-1),0) -> 342 | AD11: 7 | AE11: =5000*FLOOR(2.5*EXP(20*AD11/33),1) -> 865000 | AF11: =1000*POWER(2,AD11-1) -> 64000
A12: 8 | B12: =ROUND(30*A12*POWER(1.1,A12)*Parametres!$B$4,0) -> 2058 | C12: =B12-ROUND(30*(A12-1)*POWER(1.1,A12-1)*Parametres!$B$4,0) -> 421 | D12: =ROUND(10*A12*POWER(1.1,A12),0) -> 171 | E12: =ROUND(60*POWER(1.5,A12-1),0) -> 1025 | F12: =ROUND(15*POWER(1.5,A12-1),0) -> 256 | G12: =(E12*Parametres!$B$10+F12*Parametres!$B$11)/(C12*Parametres!$B$10)/24 -> 0.13944972 | I12: 8 | J12: =ROUND(20*I12*POWER(1.1,I12)*Parametres!$B$4,0) -> 1372 | K12: =J12-ROUND(20*(I12-1)*POWER(1.1,I12-1)*Parametres!$B$4,0) -> 281 | L12: =ROUND(10*I12*POWER(1.1,I12),0) -> 171 | M12: =ROUND(48*POWER(1.6,I12-1),0) -> 1288 | N12: =ROUND(24*POWER(1.6,I12-1),0) -> 644 | O12: =(M12*Parametres!$B$10+N12*Parametres!$B$11)/(K12*Parametres!$B$11)/24 -> 0.22281534 | Q12: 8 | R12: =ROUND(10*Q12*POWER(1.1,Q12)*Parametres!$B$4*Parametres!$B$13,0) -> 823 | S12: =R12-ROUND(10*(Q12-1)*POWER(1.1,Q12-1)*Parametres!$B$4*Parametres!$B$13,0) -> 168 | T12: =ROUND(20*Q12*POWER(1.1,Q12),0) -> 343 | U12: =ROUND(225*POWER(1.5,Q12-1),0) -> 3844 | V12: =ROUND(75*POWER(1.5,Q12-1),0) -> 1281 | W12: =(U12*Parametres!$B$10+V12*Parametres!$B$11)/(S12*Parametres!$B$12)/24 -> 0.47664517 | Y12: 8 | Z12: =ROUND(20*Y12*POWER(1.1,Y12),0) -> 343 | AA12: =ROUND(75*POWER(1.5,Y12-1),0) -> 1281 | AB12: =ROUND(30*POWER(1.5,Y12-1),0) -> 513 | AD12: 8 | AE12: =5000*FLOOR(2.5*EXP(20*AD12/33),1) -> 1590000 | AF12: =1000*POWER(2,AD12-1) -> 128000
A13: 9 | B13: =ROUND(30*A13*POWER(1.1,A13)*Parametres!$B$4,0) -> 2547 | C13: =B13-ROUND(30*(A13-1)*POWER(1.1,A13-1)*Parametres!$B$4,0) -> 489 | D13: =ROUND(10*A13*POWER(1.1,A13),0) -> 212 | E13: =ROUND(60*POWER(1.5,A13-1),0) -> 1538 | F13: =ROUND(15*POWER(1.5,A13-1),0) -> 384 | G13: =(E13*Parametres!$B$10+F13*Parametres!$B$11)/(C13*Parametres!$B$10)/24 -> 0.18012952 | I13: 9 | J13: =ROUND(20*I13*POWER(1.1,I13)*Parametres!$B$4,0) -> 1698 | K13: =J13-ROUND(20*(I13-1)*POWER(1.1,I13-1)*Parametres!$B$4,0) -> 326 | L13: =ROUND(10*I13*POWER(1.1,I13),0) -> 212 | M13: =ROUND(48*POWER(1.6,I13-1),0) -> 2062 | N13: =ROUND(24*POWER(1.6,I13-1),0) -> 1031 | O13: =(M13*Parametres!$B$10+N13*Parametres!$B$11)/(K13*Parametres!$B$11)/24 -> 0.30747273 | Q13: 9 | R13: =ROUND(10*Q13*POWER(1.1,Q13)*Parametres!$B$4*Parametres!$B$13,0) -> 1019 | S13: =R13-ROUND(10*(Q13-1)*POWER(1.1,Q13-1)*Parametres!$B$4*Parametres!$B$13,0) -> 196 | T13: =ROUND(20*Q13*POWER(1.1,Q13),0) -> 424 | U13: =ROUND(225*POWER(1.5,Q13-1),0) -> 5767 | V13: =ROUND(75*POWER(1.5,Q13-1),0) -> 1922 | W13: =(U13*Parametres!$B$10+V13*Parametres!$B$11)/(S13*Parametres!$B$12)/24 -> 0.61295351 | Y13: 9 | Z13: =ROUND(20*Y13*POWER(1.1,Y13),0) -> 424 | AA13: =ROUND(75*POWER(1.5,Y13-1),0) -> 1922 | AB13: =ROUND(30*POWER(1.5,Y13-1),0) -> 769 | AD13: 9 | AE13: =5000*FLOOR(2.5*EXP(20*AD13/33),1) -> 2920000 | AF13: =1000*POWER(2,AD13-1) -> 256000
A14: 10 | B14: =ROUND(30*A14*POWER(1.1,A14)*Parametres!$B$4,0) -> 3112 | C14: =B14-ROUND(30*(A14-1)*POWER(1.1,A14-1)*Parametres!$B$4,0) -> 565 | D14: =ROUND(10*A14*POWER(1.1,A14),0) -> 259 | E14: =ROUND(60*POWER(1.5,A14-1),0) -> 2307 | F14: =ROUND(15*POWER(1.5,A14-1),0) -> 577 | G14: =(E14*Parametres!$B$10+F14*Parametres!$B$11)/(C14*Parametres!$B$10)/24 -> 0.23396018 | I14: 10 | J14: =ROUND(20*I14*POWER(1.1,I14)*Parametres!$B$4,0) -> 2075 | K14: =J14-ROUND(20*(I14-1)*POWER(1.1,I14-1)*Parametres!$B$4,0) -> 377 | L14: =ROUND(10*I14*POWER(1.1,I14),0) -> 259 | M14: =ROUND(48*POWER(1.6,I14-1),0) -> 3299 | N14: =ROUND(24*POWER(1.6,I14-1),0) -> 1649 | O14: =(M14*Parametres!$B$10+N14*Parametres!$B$11)/(K14*Parametres!$B$11)/24 -> 0.4253242 | Q14: 10 | R14: =ROUND(10*Q14*POWER(1.1,Q14)*Parametres!$B$4*Parametres!$B$13,0) -> 1245 | S14: =R14-ROUND(10*(Q14-1)*POWER(1.1,Q14-1)*Parametres!$B$4*Parametres!$B$13,0) -> 226 | T14: =ROUND(20*Q14*POWER(1.1,Q14),0) -> 519 | U14: =ROUND(225*POWER(1.5,Q14-1),0) -> 8650 | V14: =ROUND(75*POWER(1.5,Q14-1),0) -> 2883 | W14: =(U14*Parametres!$B$10+V14*Parametres!$B$11)/(S14*Parametres!$B$12)/24 -> 0.79735128 | Y14: 10 | Z14: =ROUND(20*Y14*POWER(1.1,Y14),0) -> 519 | AA14: =ROUND(75*POWER(1.5,Y14-1),0) -> 2883 | AB14: =ROUND(30*POWER(1.5,Y14-1),0) -> 1153 | AD14: 10 | AE14: =5000*FLOOR(2.5*EXP(20*AD14/33),1) -> 5355000 | AF14: =1000*POWER(2,AD14-1) -> 512000
A15: 11 | B15: =ROUND(30*A15*POWER(1.1,A15)*Parametres!$B$4,0) -> 3766 | C15: =B15-ROUND(30*(A15-1)*POWER(1.1,A15-1)*Parametres!$B$4,0) -> 654 | D15: =ROUND(10*A15*POWER(1.1,A15),0) -> 314 | E15: =ROUND(60*POWER(1.5,A15-1),0) -> 3460 | F15: =ROUND(15*POWER(1.5,A15-1),0) -> 865 | G15: =(E15*Parametres!$B$10+F15*Parametres!$B$11)/(C15*Parametres!$B$10)/24 -> 0.3031027 | I15: 11 | J15: =ROUND(20*I15*POWER(1.1,I15)*Parametres!$B$4,0) -> 2511 | K15: =J15-ROUND(20*(I15-1)*POWER(1.1,I15-1)*Parametres!$B$4,0) -> 436 | L15: =ROUND(10*I15*POWER(1.1,I15),0) -> 314 | M15: =ROUND(48*POWER(1.6,I15-1),0) -> 5278 | N15: =ROUND(24*POWER(1.6,I15-1),0) -> 2639 | O15: =(M15*Parametres!$B$10+N15*Parametres!$B$11)/(K15*Parametres!$B$11)/24 -> 0.58846203 | Q15: 11 | R15: =ROUND(10*Q15*POWER(1.1,Q15)*Parametres!$B$4*Parametres!$B$13,0) -> 1506 | S15: =R15-ROUND(10*(Q15-1)*POWER(1.1,Q15-1)*Parametres!$B$4*Parametres!$B$13,0) -> 261 | T15: =ROUND(20*Q15*POWER(1.1,Q15),0) -> 628 | U15: =ROUND(225*POWER(1.5,Q15-1),0) -> 12975 | V15: =ROUND(75*POWER(1.5,Q15-1),0) -> 4325 | W15: =(U15*Parametres!$B$10+V15*Parametres!$B$11)/(S15*Parametres!$B$12)/24 -> 1.0356801 | Y15: 11 | Z15: =ROUND(20*Y15*POWER(1.1,Y15),0) -> 628 | AA15: =ROUND(75*POWER(1.5,Y15-1),0) -> 4325 | AB15: =ROUND(30*POWER(1.5,Y15-1),0) -> 1730 | AD15: 11 | AE15: =5000*FLOOR(2.5*EXP(20*AD15/33),1) -> 9820000 | AF15: =1000*POWER(2,AD15-1) -> 1024000
A16: 12 | B16: =ROUND(30*A16*POWER(1.1,A16)*Parametres!$B$4,0) -> 4519 | C16: =B16-ROUND(30*(A16-1)*POWER(1.1,A16-1)*Parametres!$B$4,0) -> 753 | D16: =ROUND(10*A16*POWER(1.1,A16),0) -> 377 | E16: =ROUND(60*POWER(1.5,A16-1),0) -> 5190 | F16: =ROUND(15*POWER(1.5,A16-1),0) -> 1297 | G16: =(E16*Parametres!$B$10+F16*Parametres!$B$11)/(C16*Parametres!$B$10)/24 -> 0.39483732 | I16: 12 | J16: =ROUND(20*I16*POWER(1.1,I16)*Parametres!$B$4,0) -> 3013 | K16: =J16-ROUND(20*(I16-1)*POWER(1.1,I16-1)*Parametres!$B$4,0) -> 502 | L16: =ROUND(10*I16*POWER(1.1,I16),0) -> 377 | M16: =ROUND(48*POWER(1.6,I16-1),0) -> 8444 | N16: =ROUND(24*POWER(1.6,I16-1),0) -> 4222 | O16: =(M16*Parametres!$B$10+N16*Parametres!$B$11)/(K16*Parametres!$B$11)/24 -> 0.81767375 | Q16: 12 | R16: =ROUND(10*Q16*POWER(1.1,Q16)*Parametres!$B$4*Parametres!$B$13,0) -> 1808 | S16: =R16-ROUND(10*(Q16-1)*POWER(1.1,Q16-1)*Parametres!$B$4*Parametres!$B$13,0) -> 302 | T16: =ROUND(20*Q16*POWER(1.1,Q16),0) -> 753 | U16: =ROUND(225*POWER(1.5,Q16-1),0) -> 19462 | V16: =ROUND(75*POWER(1.5,Q16-1),0) -> 6487 | W16: =(U16*Parametres!$B$10+V16*Parametres!$B$11)/(S16*Parametres!$B$12)/24 -> 1.3425543 | Y16: 12 | Z16: =ROUND(20*Y16*POWER(1.1,Y16),0) -> 753 | AA16: =ROUND(75*POWER(1.5,Y16-1),0) -> 6487 | AB16: =ROUND(30*POWER(1.5,Y16-1),0) -> 2595 | AD16: 12 | AE16: =5000*FLOOR(2.5*EXP(20*AD16/33),1) -> 18005000 | AF16: =1000*POWER(2,AD16-1) -> 2048000
... A24: 20 | B24: =ROUND(30*A24*POWER(1.1,A24)*Parametres!$B$4,0) -> 16146 | C24: =B24-ROUND(30*(A24-1)*POWER(1.1,A24-1)*Parametres!$B$4,0) -> 2202 | D24: =ROUND(10*A24*POWER(1.1,A24),0) -> 1345 | E24: =ROUND(60*POWER(1.5,A24-1),0) -> 133010 | F24: =ROUND(15*POWER(1.5,A24-1),0) -> 33253 | G24: =(E24*Parametres!$B$10+F24*Parametres!$B$11)/(C24*Parametres!$B$10)/24 -> 3.4606702 | I24: 20 | J24: =ROUND(20*I24*POWER(1.1,I24)*Parametres!$B$4,0) -> 10764 | K24: =J24-ROUND(20*(I24-1)*POWER(1.1,I24-1)*Parametres!$B$4,0) -> 1468 | L24: =ROUND(10*I24*POWER(1.1,I24),0) -> 1345 | M24: =ROUND(48*POWER(1.6,I24-1),0) -> 362678 | N24: =ROUND(24*POWER(1.6,I24-1),0) -> 181339 | O24: =(M24*Parametres!$B$10+N24*Parametres!$B$11)/(K24*Parametres!$B$11)/24 -> 12.00966 | Q24: 20 | R24: =ROUND(10*Q24*POWER(1.1,Q24)*Parametres!$B$4*Parametres!$B$13,0) -> 6458 | S24: =R24-ROUND(10*(Q24-1)*POWER(1.1,Q24-1)*Parametres!$B$4*Parametres!$B$13,0) -> 880 | T24: =ROUND(20*Q24*POWER(1.1,Q24),0) -> 2691 | U24: =ROUND(225*POWER(1.5,Q24-1),0) -> 498789 | V24: =ROUND(75*POWER(1.5,Q24-1),0) -> 166263 | W24: =(U24*Parametres!$B$10+V24*Parametres!$B$11)/(S24*Parametres!$B$12)/24 -> 11.808452 | Y24: 20 | Z24: =ROUND(20*Y24*POWER(1.1,Y24),0) -> 2691 | AA24: =ROUND(75*POWER(1.5,Y24-1),0) -> 166263 | AB24: =ROUND(30*POWER(1.5,Y24-1),0) -> 66505 | AD24: 20 | AE24: =5000*FLOOR(2.5*EXP(20*AD24/33),1) -> 2296600000 | AF24: =1000*POWER(2,AD24-1) -> 524288000
A25: 21 | B25: =ROUND(30*A25*POWER(1.1,A25)*Parametres!$B$4,0) -> 18649 | C25: =B25-ROUND(30*(A25-1)*POWER(1.1,A25-1)*Parametres!$B$4,0) -> 2503 | D25: =ROUND(10*A25*POWER(1.1,A25),0) -> 1554 | E25: =ROUND(60*POWER(1.5,A25-1),0) -> 199515 | F25: =ROUND(15*POWER(1.5,A25-1),0) -> 49879 | G25: =(E25*Parametres!$B$10+F25*Parametres!$B$11)/(C25*Parametres!$B$10)/24 -> 4.5667449 | I25: 21 | J25: =ROUND(20*I25*POWER(1.1,I25)*Parametres!$B$4,0) -> 12432 | K25: =J25-ROUND(20*(I25-1)*POWER(1.1,I25-1)*Parametres!$B$4,0) -> 1668 | L25: =ROUND(10*I25*POWER(1.1,I25),0) -> 1554 | M25: =ROUND(48*POWER(1.6,I25-1),0) -> 580284 | N25: =ROUND(24*POWER(1.6,I25-1),0) -> 290142 | O25: =(M25*Parametres!$B$10+N25*Parametres!$B$11)/(K25*Parametres!$B$11)/24 -> 16.911421 | Q25: 21 | R25: =ROUND(10*Q25*POWER(1.1,Q25)*Parametres!$B$4*Parametres!$B$13,0) -> 7459 | S25: =R25-ROUND(10*(Q25-1)*POWER(1.1,Q25-1)*Parametres!$B$4*Parametres!$B$13,0) -> 1001 | T25: =ROUND(20*Q25*POWER(1.1,Q25),0) -> 3108 | U25: =ROUND(225*POWER(1.5,Q25-1),0) -> 748183 | V25: =ROUND(75*POWER(1.5,Q25-1),0) -> 249394 | W25: =(U25*Parametres!$B$10+V25*Parametres!$B$11)/(S25*Parametres!$B$12)/24 -> 15.571567 | Y25: 21 | Z25: =ROUND(20*Y25*POWER(1.1,Y25),0) -> 3108 | AA25: =ROUND(75*POWER(1.5,Y25-1),0) -> 249394 | AB25: =ROUND(30*POWER(1.5,Y25-1),0) -> 99758
A26: 22 | B26: =ROUND(30*A26*POWER(1.1,A26)*Parametres!$B$4,0) -> 21490 | C26: =B26-ROUND(30*(A26-1)*POWER(1.1,A26-1)*Parametres!$B$4,0) -> 2841 | D26: =ROUND(10*A26*POWER(1.1,A26),0) -> 1791 | E26: =ROUND(60*POWER(1.5,A26-1),0) -> 299273 | F26: =ROUND(15*POWER(1.5,A26-1),0) -> 74818 | G26: =(E26*Parametres!$B$10+F26*Parametres!$B$11)/(C26*Parametres!$B$10)/24 -> 6.0351402 | I26: 22 | J26: =ROUND(20*I26*POWER(1.1,I26)*Parametres!$B$4,0) -> 14327 | K26: =J26-ROUND(20*(I26-1)*POWER(1.1,I26-1)*Parametres!$B$4,0) -> 1895 | L26: =ROUND(10*I26*POWER(1.1,I26),0) -> 1791 | M26: =ROUND(48*POWER(1.6,I26-1),0) -> 928455 | N26: =ROUND(24*POWER(1.6,I26-1),0) -> 464228 | O26: =(M26*Parametres!$B$10+N26*Parametres!$B$11)/(K26*Parametres!$B$11)/24 -> 23.817018 | Q26: 22 | R26: =ROUND(10*Q26*POWER(1.1,Q26)*Parametres!$B$4*Parametres!$B$13,0) -> 8596 | S26: =R26-ROUND(10*(Q26-1)*POWER(1.1,Q26-1)*Parametres!$B$4*Parametres!$B$13,0) -> 1137 | T26: =ROUND(20*Q26*POWER(1.1,Q26),0) -> 3582 | U26: =ROUND(225*POWER(1.5,Q26-1),0) -> 1122274 | V26: =ROUND(75*POWER(1.5,Q26-1),0) -> 374091 | W26: =(U26*Parametres!$B$10+V26*Parametres!$B$11)/(S26*Parametres!$B$12)/24 -> 20.563502 | Y26: 22 | Z26: =ROUND(20*Y26*POWER(1.1,Y26),0) -> 3582 | AA26: =ROUND(75*POWER(1.5,Y26-1),0) -> 374091 | AB26: =ROUND(30*POWER(1.5,Y26-1),0) -> 149637
A27: 23 | B27: =ROUND(30*A27*POWER(1.1,A27)*Parametres!$B$4,0) -> 24714 | C27: =B27-ROUND(30*(A27-1)*POWER(1.1,A27-1)*Parametres!$B$4,0) -> 3224 | D27: =ROUND(10*A27*POWER(1.1,A27),0) -> 2059 | E27: =ROUND(60*POWER(1.5,A27-1),0) -> 448910 | F27: =ROUND(15*POWER(1.5,A27-1),0) -> 112227 | G27: =(E27*Parametres!$B$10+F27*Parametres!$B$11)/(C27*Parametres!$B$10)/24 -> 7.9772862 | I27: 23 | J27: =ROUND(20*I27*POWER(1.1,I27)*Parametres!$B$4,0) -> 16476 | K27: =J27-ROUND(20*(I27-1)*POWER(1.1,I27-1)*Parametres!$B$4,0) -> 2149 | L27: =ROUND(10*I27*POWER(1.1,I27),0) -> 2059 | M27: =ROUND(48*POWER(1.6,I27-1),0) -> 1485528 | N27: =ROUND(24*POWER(1.6,I27-1),0) -> 742764 | O27: =(M27*Parametres!$B$10+N27*Parametres!$B$11)/(K27*Parametres!$B$11)/24 -> 33.603149 | Q27: 23 | R27: =ROUND(10*Q27*POWER(1.1,Q27)*Parametres!$B$4*Parametres!$B$13,0) -> 9886 | S27: =R27-ROUND(10*(Q27-1)*POWER(1.1,Q27-1)*Parametres!$B$4*Parametres!$B$13,0) -> 1290 | T27: =ROUND(20*Q27*POWER(1.1,Q27),0) -> 4119 | U27: =ROUND(225*POWER(1.5,Q27-1),0) -> 1683411 | V27: =ROUND(75*POWER(1.5,Q27-1),0) -> 561137 | W27: =(U27*Parametres!$B$10+V27*Parametres!$B$11)/(S27*Parametres!$B$12)/24 -> 27.18687 | Y27: 23 | Z27: =ROUND(20*Y27*POWER(1.1,Y27),0) -> 4119 | AA27: =ROUND(75*POWER(1.5,Y27-1),0) -> 561137 | AB27: =ROUND(30*POWER(1.5,Y27-1),0) -> 224455
A28: 24 | B28: =ROUND(30*A28*POWER(1.1,A28)*Parametres!$B$4,0) -> 28367 | C28: =B28-ROUND(30*(A28-1)*POWER(1.1,A28-1)*Parametres!$B$4,0) -> 3653 | D28: =ROUND(10*A28*POWER(1.1,A28),0) -> 2364 | E28: =ROUND(60*POWER(1.5,A28-1),0) -> 673364 | F28: =ROUND(15*POWER(1.5,A28-1),0) -> 168341 | G28: =(E28*Parametres!$B$10+F28*Parametres!$B$11)/(C28*Parametres!$B$10)/24 -> 10.560675 | I28: 24 | J28: =ROUND(20*I28*POWER(1.1,I28)*Parametres!$B$4,0) -> 18911 | K28: =J28-ROUND(20*(I28-1)*POWER(1.1,I28-1)*Parametres!$B$4,0) -> 2435 | L28: =ROUND(10*I28*POWER(1.1,I28),0) -> 2364 | M28: =ROUND(48*POWER(1.6,I28-1),0) -> 2376845 | N28: =ROUND(24*POWER(1.6,I28-1),0) -> 1188422 | O28: =(M28*Parametres!$B$10+N28*Parametres!$B$11)/(K28*Parametres!$B$11)/24 -> 47.450125 | Q28: 24 | R28: =ROUND(10*Q28*POWER(1.1,Q28)*Parametres!$B$4*Parametres!$B$13,0) -> 11347 | S28: =R28-ROUND(10*(Q28-1)*POWER(1.1,Q28-1)*Parametres!$B$4*Parametres!$B$13,0) -> 1461 | T28: =ROUND(20*Q28*POWER(1.1,Q28),0) -> 4728 | U28: =ROUND(225*POWER(1.5,Q28-1),0) -> 2525117 | V28: =ROUND(75*POWER(1.5,Q28-1),0) -> 841706 | W28: =(U28*Parametres!$B$10+V28*Parametres!$B$11)/(S28*Parametres!$B$12)/24 -> 36.007263 | Y28: 24 | Z28: =ROUND(20*Y28*POWER(1.1,Y28),0) -> 4728 | AA28: =ROUND(75*POWER(1.5,Y28-1),0) -> 841706 | AB28: =ROUND(30*POWER(1.5,Y28-1),0) -> 336682
A29: 25 | B29: =ROUND(30*A29*POWER(1.1,A29)*Parametres!$B$4,0) -> 32504 | C29: =B29-ROUND(30*(A29-1)*POWER(1.1,A29-1)*Parametres!$B$4,0) -> 4137 | D29: =ROUND(10*A29*POWER(1.1,A29),0) -> 2709 | E29: =ROUND(60*POWER(1.5,A29-1),0) -> 1010047 | F29: =ROUND(15*POWER(1.5,A29-1),0) -> 252512 | G29: =(E29*Parametres!$B$10+F29*Parametres!$B$11)/(C29*Parametres!$B$10)/24 -> 13.987743 | I29: 25 | J29: =ROUND(20*I29*POWER(1.1,I29)*Parametres!$B$4,0) -> 21669 | K29: =J29-ROUND(20*(I29-1)*POWER(1.1,I29-1)*Parametres!$B$4,0) -> 2758 | L29: =ROUND(10*I29*POWER(1.1,I29),0) -> 2709 | M29: =ROUND(48*POWER(1.6,I29-1),0) -> 3802952 | N29: =ROUND(24*POWER(1.6,I29-1),0) -> 1901476 | O29: =(M29*Parametres!$B$10+N29*Parametres!$B$11)/(K29*Parametres!$B$11)/24 -> 67.028906 | Q29: 25 | R29: =ROUND(10*Q29*POWER(1.1,Q29)*Parametres!$B$4*Parametres!$B$13,0) -> 13002 | S29: =R29-ROUND(10*(Q29-1)*POWER(1.1,Q29-1)*Parametres!$B$4*Parametres!$B$13,0) -> 1655 | T29: =ROUND(20*Q29*POWER(1.1,Q29),0) -> 5417 | U29: =ROUND(225*POWER(1.5,Q29-1),0) -> 3787675 | V29: =ROUND(75*POWER(1.5,Q29-1),0) -> 1262558 | W29: =(U29*Parametres!$B$10+V29*Parametres!$B$11)/(S29*Parametres!$B$12)/24 -> 47.679691 | Y29: 25 | Z29: =ROUND(20*Y29*POWER(1.1,Y29),0) -> 5417 | AA29: =ROUND(75*POWER(1.5,Y29-1),0) -> 1262558 | AB29: =ROUND(30*POWER(1.5,Y29-1),0) -> 505023
A30: 26 | B30: =ROUND(30*A30*POWER(1.1,A30)*Parametres!$B$4,0) -> 37185 | C30: =B30-ROUND(30*(A30-1)*POWER(1.1,A30-1)*Parametres!$B$4,0) -> 4681 | D30: =ROUND(10*A30*POWER(1.1,A30),0) -> 3099 | E30: =ROUND(60*POWER(1.5,A30-1),0) -> 1515070 | F30: =ROUND(15*POWER(1.5,A30-1),0) -> 378768 | G30: =(E30*Parametres!$B$10+F30*Parametres!$B$11)/(C30*Parametres!$B$10)/24 -> 18.543242 | I30: 26 | J30: =ROUND(20*I30*POWER(1.1,I30)*Parametres!$B$4,0) -> 24790 | K30: =J30-ROUND(20*(I30-1)*POWER(1.1,I30-1)*Parametres!$B$4,0) -> 3121 | L30: =ROUND(10*I30*POWER(1.1,I30),0) -> 3099 | M30: =ROUND(48*POWER(1.6,I30-1),0) -> 6084723 | N30: =ROUND(24*POWER(1.6,I30-1),0) -> 3042361 | O30: =(M30*Parametres!$B$10+N30*Parametres!$B$11)/(K30*Parametres!$B$11)/24 -> 94.772549 | Q30: 26 | R30: =ROUND(10*Q30*POWER(1.1,Q30)*Parametres!$B$4*Parametres!$B$13,0) -> 14874 | S30: =R30-ROUND(10*(Q30-1)*POWER(1.1,Q30-1)*Parametres!$B$4*Parametres!$B$13,0) -> 1872 | T30: =ROUND(20*Q30*POWER(1.1,Q30),0) -> 6197 | U30: =ROUND(225*POWER(1.5,Q30-1),0) -> 5681513 | V30: =ROUND(75*POWER(1.5,Q30-1),0) -> 1893838 | W30: =(U30*Parametres!$B$10+V30*Parametres!$B$11)/(S30*Parametres!$B$12)/24 -> 63.229092 | Y30: 26 | Z30: =ROUND(20*Y30*POWER(1.1,Y30),0) -> 6197 | AA30: =ROUND(75*POWER(1.5,Y30-1),0) -> 1893838 | AB30: =ROUND(30*POWER(1.5,Y30-1),0) -> 757535
A31: 27 | B31: =ROUND(30*A31*POWER(1.1,A31)*Parametres!$B$4,0) -> 42476 | C31: =B31-ROUND(30*(A31-1)*POWER(1.1,A31-1)*Parametres!$B$4,0) -> 5291 | D31: =ROUND(10*A31*POWER(1.1,A31),0) -> 3540 | E31: =ROUND(60*POWER(1.5,A31-1),0) -> 2272605 | F31: =ROUND(15*POWER(1.5,A31-1),0) -> 568151 | G31: =(E31*Parametres!$B$10+F31*Parametres!$B$11)/(C31*Parametres!$B$10)/24 -> 24.608073 | I31: 27 | J31: =ROUND(20*I31*POWER(1.1,I31)*Parametres!$B$4,0) -> 28318 | K31: =J31-ROUND(20*(I31-1)*POWER(1.1,I31-1)*Parametres!$B$4,0) -> 3528 | L31: =ROUND(10*I31*POWER(1.1,I31),0) -> 3540 | M31: =ROUND(48*POWER(1.6,I31-1),0) -> 9735557 | N31: =ROUND(24*POWER(1.6,I31-1),0) -> 4867778 | O31: =(M31*Parametres!$B$10+N31*Parametres!$B$11)/(K31*Parametres!$B$11)/24 -> 134.14292 | Q31: 27 | R31: =ROUND(10*Q31*POWER(1.1,Q31)*Parametres!$B$4*Parametres!$B$13,0) -> 16991 | S31: =R31-ROUND(10*(Q31-1)*POWER(1.1,Q31-1)*Parametres!$B$4*Parametres!$B$13,0) -> 2117 | T31: =ROUND(20*Q31*POWER(1.1,Q31),0) -> 7079 | U31: =ROUND(225*POWER(1.5,Q31-1),0) -> 8522269 | V31: =ROUND(75*POWER(1.5,Q31-1),0) -> 2840756 | W31: =(U31*Parametres!$B$10+V31*Parametres!$B$11)/(S31*Parametres!$B$12)/24 -> 83.86739 | Y31: 27 | Z31: =ROUND(20*Y31*POWER(1.1,Y31),0) -> 7079 | AA31: =ROUND(75*POWER(1.5,Y31-1),0) -> 2840756 | AB31: =ROUND(30*POWER(1.5,Y31-1),0) -> 1136303
A32: 28 | B32: =ROUND(30*A32*POWER(1.1,A32)*Parametres!$B$4,0) -> 48455 | C32: =B32-ROUND(30*(A32-1)*POWER(1.1,A32-1)*Parametres!$B$4,0) -> 5979 | D32: =ROUND(10*A32*POWER(1.1,A32),0) -> 4038 | E32: =ROUND(60*POWER(1.5,A32-1),0) -> 3408908 | F32: =ROUND(15*POWER(1.5,A32-1),0) -> 852227 | G32: =(E32*Parametres!$B$10+F32*Parametres!$B$11)/(C32*Parametres!$B$10)/24 -> 32.664663 | I32: 28 | J32: =ROUND(20*I32*POWER(1.1,I32)*Parametres!$B$4,0) -> 32303 | K32: =J32-ROUND(20*(I32-1)*POWER(1.1,I32-1)*Parametres!$B$4,0) -> 3985 | L32: =ROUND(10*I32*POWER(1.1,I32),0) -> 4038 | M32: =ROUND(48*POWER(1.6,I32-1),0) -> 15576891 | N32: =ROUND(24*POWER(1.6,I32-1),0) -> 7788445 | O32: =(M32*Parametres!$B$10+N32*Parametres!$B$11)/(K32*Parametres!$B$11)/24 -> 190.01505 | Q32: 28 | R32: =ROUND(10*Q32*POWER(1.1,Q32)*Parametres!$B$4*Parametres!$B$13,0) -> 19382 | S32: =R32-ROUND(10*(Q32-1)*POWER(1.1,Q32-1)*Parametres!$B$4*Parametres!$B$13,0) -> 2391 | T32: =ROUND(20*Q32*POWER(1.1,Q32),0) -> 8076 | U32: =ROUND(225*POWER(1.5,Q32-1),0) -> 12783404 | V32: =ROUND(75*POWER(1.5,Q32-1),0) -> 4261135 | W32: =(U32*Parametres!$B$10+V32*Parametres!$B$11)/(S32*Parametres!$B$12)/24 -> 111.38474 | Y32: 28 | Z32: =ROUND(20*Y32*POWER(1.1,Y32),0) -> 8076 | AA32: =ROUND(75*POWER(1.5,Y32-1),0) -> 4261135 | AB32: =ROUND(30*POWER(1.5,Y32-1),0) -> 1704454
A33: 29 | B33: =ROUND(30*A33*POWER(1.1,A33)*Parametres!$B$4,0) -> 55204 | C33: =B33-ROUND(30*(A33-1)*POWER(1.1,A33-1)*Parametres!$B$4,0) -> 6749 | D33: =ROUND(10*A33*POWER(1.1,A33),0) -> 4600 | E33: =ROUND(60*POWER(1.5,A33-1),0) -> 5113362 | F33: =ROUND(15*POWER(1.5,A33-1),0) -> 1278340 | G33: =(E33*Parametres!$B$10+F33*Parametres!$B$11)/(C33*Parametres!$B$10)/24 -> 43.406875 | I33: 29 | J33: =ROUND(20*I33*POWER(1.1,I33)*Parametres!$B$4,0) -> 36802 | K33: =J33-ROUND(20*(I33-1)*POWER(1.1,I33-1)*Parametres!$B$4,0) -> 4499 | L33: =ROUND(10*I33*POWER(1.1,I33),0) -> 4600 | M33: =ROUND(48*POWER(1.6,I33-1),0) -> 24923025 | N33: =ROUND(24*POWER(1.6,I33-1),0) -> 12461512 | O33: =(M33*Parametres!$B$10+N33*Parametres!$B$11)/(K33*Parametres!$B$11)/24 -> 269.29005 | Q33: 29 | R33: =ROUND(10*Q33*POWER(1.1,Q33)*Parametres!$B$4*Parametres!$B$13,0) -> 22081 | S33: =R33-ROUND(10*(Q33-1)*POWER(1.1,Q33-1)*Parametres!$B$4*Parametres!$B$13,0) -> 2699 | T33: =ROUND(20*Q33*POWER(1.1,Q33),0) -> 9201 | U33: =ROUND(225*POWER(1.5,Q33-1),0) -> 19175106 | V33: =ROUND(75*POWER(1.5,Q33-1),0) -> 6391702 | W33: =(U33*Parametres!$B$10+V33*Parametres!$B$11)/(S33*Parametres!$B$12)/24 -> 148.01088 | Y33: 29 | Z33: =ROUND(20*Y33*POWER(1.1,Y33),0) -> 9201 | AA33: =ROUND(75*POWER(1.5,Y33-1),0) -> 6391702 | AB33: =ROUND(30*POWER(1.5,Y33-1),0) -> 2556681
A34: 30 | B34: =ROUND(30*A34*POWER(1.1,A34)*Parametres!$B$4,0) -> 62818 | C34: =B34-ROUND(30*(A34-1)*POWER(1.1,A34-1)*Parametres!$B$4,0) -> 7614 | D34: =ROUND(10*A34*POWER(1.1,A34),0) -> 5235 | E34: =ROUND(60*POWER(1.5,A34-1),0) -> 7670042 | F34: =ROUND(15*POWER(1.5,A34-1),0) -> 1917511 | G34: =(E34*Parametres!$B$10+F34*Parametres!$B$11)/(C34*Parametres!$B$10)/24 -> 57.71336 | I34: 30 | J34: =ROUND(20*I34*POWER(1.1,I34)*Parametres!$B$4,0) -> 41879 | K34: =J34-ROUND(20*(I34-1)*POWER(1.1,I34-1)*Parametres!$B$4,0) -> 5077 | L34: =ROUND(10*I34*POWER(1.1,I34),0) -> 5235 | M34: =ROUND(48*POWER(1.6,I34-1),0) -> 39876840 | N34: =ROUND(24*POWER(1.6,I34-1),0) -> 19938420 | O34: =(M34*Parametres!$B$10+N34*Parametres!$B$11)/(K34*Parametres!$B$11)/24 -> 381.8116 | Q34: 30 | R34: =ROUND(10*Q34*POWER(1.1,Q34)*Parametres!$B$4*Parametres!$B$13,0) -> 25127 | S34: =R34-ROUND(10*(Q34-1)*POWER(1.1,Q34-1)*Parametres!$B$4*Parametres!$B$13,0) -> 3046 | T34: =ROUND(20*Q34*POWER(1.1,Q34),0) -> 10470 | U34: =ROUND(225*POWER(1.5,Q34-1),0) -> 28762659 | V34: =ROUND(75*POWER(1.5,Q34-1),0) -> 9587553 | W34: =(U34*Parametres!$B$10+V34*Parametres!$B$11)/(S34*Parametres!$B$12)/24 -> 196.72425 | Y34: 30 | Z34: =ROUND(20*Y34*POWER(1.1,Y34),0) -> 10470 | AA34: =ROUND(75*POWER(1.5,Y34-1),0) -> 9587553 | AB34: =ROUND(30*POWER(1.5,Y34-1),0) -> 3835021
A35: 31 | B35: =ROUND(30*A35*POWER(1.1,A35)*Parametres!$B$4,0) -> 71403 | C35: =B35-ROUND(30*(A35-1)*POWER(1.1,A35-1)*Parametres!$B$4,0) -> 8585 | D35: =ROUND(10*A35*POWER(1.1,A35),0) -> 5950 | E35: =ROUND(60*POWER(1.5,A35-1),0) -> 11505064 | F35: =ROUND(15*POWER(1.5,A35-1),0) -> 2876266 | G35: =(E35*Parametres!$B$10+F35*Parametres!$B$11)/(C35*Parametres!$B$10)/24 -> 76.778601 | I35: 31 | J35: =ROUND(20*I35*POWER(1.1,I35)*Parametres!$B$4,0) -> 47602 | K35: =J35-ROUND(20*(I35-1)*POWER(1.1,I35-1)*Parametres!$B$4,0) -> 5723 | L35: =ROUND(10*I35*POWER(1.1,I35),0) -> 5950 | M35: =ROUND(48*POWER(1.6,I35-1),0) -> 63802944 | N35: =ROUND(24*POWER(1.6,I35-1),0) -> 31901472 | O35: =(M35*Parametres!$B$10+N35*Parametres!$B$11)/(K35*Parametres!$B$11)/24 -> 541.94164 | Q35: 31 | R35: =ROUND(10*Q35*POWER(1.1,Q35)*Parametres!$B$4*Parametres!$B$13,0) -> 28561 | S35: =R35-ROUND(10*(Q35-1)*POWER(1.1,Q35-1)*Parametres!$B$4*Parametres!$B$13,0) -> 3434 | T35: =ROUND(20*Q35*POWER(1.1,Q35),0) -> 11900 | U35: =ROUND(225*POWER(1.5,Q35-1),0) -> 43143988 | V35: =ROUND(75*POWER(1.5,Q35-1),0) -> 14381329 | W35: =(U35*Parametres!$B$10+V35*Parametres!$B$11)/(S35*Parametres!$B$12)/24 -> 261.74522 | Y35: 31 | Z35: =ROUND(20*Y35*POWER(1.1,Y35),0) -> 11900 | AA35: =ROUND(75*POWER(1.5,Y35-1),0) -> 14381329 | AB35: =ROUND(30*POWER(1.5,Y35-1),0) -> 5752532
A36: 32 | B36: =ROUND(30*A36*POWER(1.1,A36)*Parametres!$B$4,0) -> 81077 | C36: =B36-ROUND(30*(A36-1)*POWER(1.1,A36-1)*Parametres!$B$4,0) -> 9674 | D36: =ROUND(10*A36*POWER(1.1,A36),0) -> 6756 | E36: =ROUND(60*POWER(1.5,A36-1),0) -> 17257595 | F36: =ROUND(15*POWER(1.5,A36-1),0) -> 4314399 | G36: =(E36*Parametres!$B$10+F36*Parametres!$B$11)/(C36*Parametres!$B$10)/24 -> 102.20347 | I36: 32 | J36: =ROUND(20*I36*POWER(1.1,I36)*Parametres!$B$4,0) -> 54051 | K36: =J36-ROUND(20*(I36-1)*POWER(1.1,I36-1)*Parametres!$B$4,0) -> 6449 | L36: =ROUND(10*I36*POWER(1.1,I36),0) -> 6756 | M36: =ROUND(48*POWER(1.6,I36-1),0) -> 102084710 | N36: =ROUND(24*POWER(1.6,I36-1),0) -> 51042355 | O36: =(M36*Parametres!$B$10+N36*Parametres!$B$11)/(K36*Parametres!$B$11)/24 -> 769.49158 | Q36: 32 | R36: =ROUND(10*Q36*POWER(1.1,Q36)*Parametres!$B$4*Parametres!$B$13,0) -> 32431 | S36: =R36-ROUND(10*(Q36-1)*POWER(1.1,Q36-1)*Parametres!$B$4*Parametres!$B$13,0) -> 3870 | T36: =ROUND(20*Q36*POWER(1.1,Q36),0) -> 13513 | U36: =ROUND(225*POWER(1.5,Q36-1),0) -> 64715982 | V36: =ROUND(75*POWER(1.5,Q36-1),0) -> 21571994 | W36: =(U36*Parametres!$B$10+V36*Parametres!$B$11)/(S36*Parametres!$B$12)/24 -> 348.38492 | Y36: 32 | Z36: =ROUND(20*Y36*POWER(1.1,Y36),0) -> 13513 | AA36: =ROUND(75*POWER(1.5,Y36-1),0) -> 21571994 | AB36: =ROUND(30*POWER(1.5,Y36-1),0) -> 8628798
... A44: 40 | B44: =ROUND(30*A44*POWER(1.1,A44)*Parametres!$B$4,0) -> 217244 | C44: =B44-ROUND(30*(A44-1)*POWER(1.1,A44-1)*Parametres!$B$4,0) -> 24686 | D44: =ROUND(10*A44*POWER(1.1,A44),0) -> 18104 | E44: =ROUND(60*POWER(1.5,A44-1),0) -> 442293293 | F44: =ROUND(15*POWER(1.5,A44-1),0) -> 110573323 | G44: =(E44*Parametres!$B$10+F44*Parametres!$B$11)/(C44*Parametres!$B$10)/24 -> 1026.4814 | I44: 40 | J44: =ROUND(20*I44*POWER(1.1,I44)*Parametres!$B$4,0) -> 144830 | K44: =J44-ROUND(20*(I44-1)*POWER(1.1,I44-1)*Parametres!$B$4,0) -> 16458 | L44: =ROUND(10*I44*POWER(1.1,I44),0) -> 18104 | M44: =ROUND(48*POWER(1.6,I44-1),0) -> 4384504912 | N44: =ROUND(24*POWER(1.6,I44-1),0) -> 2192252456 | O44: =(M44*Parametres!$B$10+N44*Parametres!$B$11)/(K44*Parametres!$B$11)/24 -> 12950.277 | Q44: 40 | R44: =ROUND(10*Q44*POWER(1.1,Q44)*Parametres!$B$4*Parametres!$B$13,0) -> 86898 | S44: =R44-ROUND(10*(Q44-1)*POWER(1.1,Q44-1)*Parametres!$B$4*Parametres!$B$13,0) -> 9875 | T44: =ROUND(20*Q44*POWER(1.1,Q44),0) -> 36207 | U44: =ROUND(225*POWER(1.5,Q44-1),0) -> 1658599848 | V44: =ROUND(75*POWER(1.5,Q44-1),0) -> 552866616 | W44: =(U44*Parametres!$B$10+V44*Parametres!$B$11)/(S44*Parametres!$B$12)/24 -> 3499.1558 | Y44: 40 | Z44: =ROUND(20*Y44*POWER(1.1,Y44),0) -> 36207 | AA44: =ROUND(75*POWER(1.5,Y44-1),0) -> 552866616 | AB44: =ROUND(30*POWER(1.5,Y44-1),0) -> 221146646

Sheet Batiments
A1: Bâtiments de support — coût au niveau N
A3: Niveau N à afficher : | B3: 10
A5: Bâtiment (FR / EN) | B5: Base Acier | C5: Base Comp. | D5: Base Carb. | E5: Facteur | F5: Coût Acier (N) | G5: Coût Comp. (N) | H5: Coût Carb. (N) | I5: Éq. acier (N)
A6: Corps du génie / Engineering Corps | B6: 400 | C6: 120 | D6: 200 | E6: 2 | F6: =ROUND(B6*POWER(E6,$B$3-1),0) -> 204800 | G6: =ROUND(C6*POWER(E6,$B$3-1),0) -> 61440 | H6: =ROUND(D6*POWER(E6,$B$3-1),0) -> 102400 | I6: =F6*Parametres!$B$10+G6*Parametres!$B$11+H6*Parametres!$B$12 -> 604160
A7: Chantier automatisé / Automated Yard | B7: 1000000 | C7: 500000 | D7: 100000 | E7: 2 | F7: =ROUND(B7*POWER(E7,$B$3-1),0) -> 512000000 | G7: =ROUND(C7*POWER(E7,$B$3-1),0) -> 256000000 | H7: =ROUND(D7*POWER(E7,$B$3-1),0) -> 51200000 | I7: =F7*Parametres!$B$10+G7*Parametres!$B$11+H7*Parametres!$B$12 -> 1049600000
A8: Usine de véhicules / Vehicle Factory | B8: 400 | C8: 200 | D8: 100 | E8: 2 | F8: =ROUND(B8*POWER(E8,$B$3-1),0) -> 204800 | G8: =ROUND(C8*POWER(E8,$B$3-1),0) -> 102400 | H8: =ROUND(D8*POWER(E8,$B$3-1),0) -> 51200 | I8: =F8*Parametres!$B$10+G8*Parametres!$B$11+H8*Parametres!$B$12 -> 512000
A9: Centre de recherche / Research Center | B9: 200 | C9: 400 | D9: 200 | E9: 2 | F9: =ROUND(B9*POWER(E9,$B$3-1),0) -> 102400 | G9: =ROUND(C9*POWER(E9,$B$3-1),0) -> 204800 | H9: =ROUND(D9*POWER(E9,$B$3-1),0) -> 102400 | I9: =F9*Parametres!$B$10+G9*Parametres!$B$11+H9*Parametres!$B$12 -> 716800
A10: Silo de missiles / Missile Silo | B10: 20000 | C10: 20000 | D10: 1000 | E10: 2 | F10: =ROUND(B10*POWER(E10,$B$3-1),0) -> 10240000 | G10: =ROUND(C10*POWER(E10,$B$3-1),0) -> 10240000 | H10: =ROUND(D10*POWER(E10,$B$3-1),0) -> 512000 | I10: =F10*Parametres!$B$10+G10*Parametres!$B$11+H10*Parametres!$B$12 -> 27136000
A11: Terrassement / Land Clearing | B11: 0 | C11: 50000 | D11: 100000 | E11: 2 | F11: =ROUND(B11*POWER(E11,$B$3-1),0) -> 0 | G11: =ROUND(C11*POWER(E11,$B$3-1),0) -> 25600000 | H11: =ROUND(D11*POWER(E11,$B$3-1),0) -> 51200000 | I11: =F11*Parametres!$B$10+G11*Parametres!$B$11+H11*Parametres!$B$12 -> 192000000
A12: Poste logistique allié / Allied Logistics | B12: 20000 | C12: 40000 | D12: 0 | E12: 2 | F12: =ROUND(B12*POWER(E12,$B$3-1),0) -> 10240000 | G12: =ROUND(C12*POWER(E12,$B$3-1),0) -> 20480000 | H12: =ROUND(D12*POWER(E12,$B$3-1),0) -> 0 | I12: =F12*Parametres!$B$10+G12*Parametres!$B$11+H12*Parametres!$B$12 -> 40960000
A13: Réacteur avancé / Advanced Reactor | B13: 900 | C13: 360 | D13: 180 | E13: 1.8 | F13: =ROUND(B13*POWER(E13,$B$3-1),0) -> 178523 | G13: =ROUND(C13*POWER(E13,$B$3-1),0) -> 71409 | H13: =ROUND(D13*POWER(E13,$B$3-1),0) -> 35705 | I13: =F13*Parametres!$B$10+G13*Parametres!$B$11+H13*Parametres!$B$12 -> 392751.5
A14: Bunker : Base souterraine / Lunar Base | B14: 20000 | C14: 40000 | D14: 20000 | E14: 2 | F14: =ROUND(B14*POWER(E14,$B$3-1),0) -> 10240000 | G14: =ROUND(C14*POWER(E14,$B$3-1),0) -> 20480000 | H14: =ROUND(D14*POWER(E14,$B$3-1),0) -> 10240000 | I14: =F14*Parametres!$B$10+G14*Parametres!$B$11+H14*Parametres!$B$12 -> 71680000
A15: Bunker : Station radar / Long-Range Radar | B15: 20000 | C15: 40000 | D15: 20000 | E15: 2 | F15: =ROUND(B15*POWER(E15,$B$3-1),0) -> 10240000 | G15: =ROUND(C15*POWER(E15,$B$3-1),0) -> 20480000 | H15: =ROUND(D15*POWER(E15,$B$3-1),0) -> 10240000 | I15: =F15*Parametres!$B$10+G15*Parametres!$B$11+H15*Parametres!$B$12 -> 71680000
A16: Bunker : Gare souterraine / Underground Rwy | B16: 2000000 | C16: 4000000 | D16: 2000000 | E16: 2 | F16: =ROUND(B16*POWER(E16,$B$3-1),0) -> 1024000000 | G16: =ROUND(C16*POWER(E16,$B$3-1),0) -> 2048000000 | H16: =ROUND(D16*POWER(E16,$B$3-1),0) -> 1024000000 | I16: =F16*Parametres!$B$10+G16*Parametres!$B$11+H16*Parametres!$B$12 -> 7168000000
A18: Coûts de base = valeurs OGame (métal→acier, cristal→composants, deutérium→carburant). Bleu = modifiable.

Sheet Recherches
A1: Technologies — coût au niveau N
A3: Niveau N à afficher : | B3: 8
A5: Technologie (FR / EN) | B5: Base Acier | C5: Base Comp. | D5: Base Carb. | E5: Facteur | F5: Coût Acier (N) | G5: Coût Comp. (N) | H5: Coût Carb. (N) | I5: Éq. acier (N)
A6: Renseignement / Signals Intelligence | B6: 200 | C6: 1000 | D6: 200 | E6: 2 | F6: =ROUND(B6*POWER(E6,$B$3-1),0) -> 25600 | G6: =ROUND(C6*POWER(E6,$B$3-1),0) -> 128000 | H6: =ROUND(D6*POWER(E6,$B$3-1),0) -> 25600 | I6: =F6*Parametres!$B$10+G6*Parametres!$B$11+H6*Parametres!$B$12 -> 294400
A7: Réseau de commandement / Command Network | B7: 0 | C7: 400 | D7: 600 | E7: 2 | F7: =ROUND(B7*POWER(E7,$B$3-1),0) -> 0 | G7: =ROUND(C7*POWER(E7,$B$3-1),0) -> 51200 | H7: =ROUND(D7*POWER(E7,$B$3-1),0) -> 76800 | I7: =F7*Parametres!$B$10+G7*Parametres!$B$11+H7*Parametres!$B$12 -> 307200
A8: Balistique / Ballistics | B8: 800 | C8: 200 | D8: 0 | E8: 2 | F8: =ROUND(B8*POWER(E8,$B$3-1),0) -> 102400 | G8: =ROUND(C8*POWER(E8,$B$3-1),0) -> 25600 | H8: =ROUND(D8*POWER(E8,$B$3-1),0) -> 0 | I8: =F8*Parametres!$B$10+G8*Parametres!$B$11+H8*Parametres!$B$12 -> 140800
A9: Systèmes défensifs / Defensive Systems | B9: 200 | C9: 600 | D9: 0 | E9: 2 | F9: =ROUND(B9*POWER(E9,$B$3-1),0) -> 25600 | G9: =ROUND(C9*POWER(E9,$B$3-1),0) -> 76800 | H9: =ROUND(D9*POWER(E9,$B$3-1),0) -> 0 | I9: =F9*Parametres!$B$10+G9*Parametres!$B$11+H9*Parametres!$B$12 -> 140800
A10: Blindage / Armor Plating | B10: 1000 | C10: 0 | D10: 0 | E10: 2 | F10: =ROUND(B10*POWER(E10,$B$3-1),0) -> 128000 | G10: =ROUND(C10*POWER(E10,$B$3-1),0) -> 0 | H10: =ROUND(D10*POWER(E10,$B$3-1),0) -> 0 | I10: =F10*Parametres!$B$10+G10*Parametres!$B$11+H10*Parametres!$B$12 -> 128000
A11: Technologie énergétique / Energy Tech | B11: 0 | C11: 800 | D11: 400 | E11: 2 | F11: =ROUND(B11*POWER(E11,$B$3-1),0) -> 0 | G11: =ROUND(C11*POWER(E11,$B$3-1),0) -> 102400 | H11: =ROUND(D11*POWER(E11,$B$3-1),0) -> 51200 | I11: =F11*Parametres!$B$10+G11*Parametres!$B$11+H11*Parametres!$B$12 -> 307200
A12: Moteurs diesel / Diesel Engines | B12: 400 | C12: 0 | D12: 600 | E12: 2 | F12: =ROUND(B12*POWER(E12,$B$3-1),0) -> 51200 | G12: =ROUND(C12*POWER(E12,$B$3-1),0) -> 0 | H12: =ROUND(D12*POWER(E12,$B$3-1),0) -> 76800 | I12: =F12*Parametres!$B$10+G12*Parametres!$B$11+H12*Parametres!$B$12 -> 281600
A13: Turbines / Turbine Engines | B13: 2000 | C13: 4000 | D13: 600 | E13: 2 | F13: =ROUND(B13*POWER(E13,$B$3-1),0) -> 256000 | G13: =ROUND(C13*POWER(E13,$B$3-1),0) -> 512000 | H13: =ROUND(D13*POWER(E13,$B$3-1),0) -> 76800 | I13: =F13*Parametres!$B$10+G13*Parametres!$B$11+H13*Parametres!$B$12 -> 1254400
A14: Sustentation magnétique / Maglev | B14: 10000 | C14: 20000 | D14: 6000 | E14: 2 | F14: =ROUND(B14*POWER(E14,$B$3-1),0) -> 1280000 | G14: =ROUND(C14*POWER(E14,$B$3-1),0) -> 2560000 | H14: =ROUND(D14*POWER(E14,$B$3-1),0) -> 768000 | I14: =F14*Parametres!$B$10+G14*Parametres!$B$11+H14*Parametres!$B$12 -> 7424000
A15: Logistique avancée / Advanced Logistics | B15: 0 | C15: 4000 | D15: 2000 | E15: 2 | F15: =ROUND(B15*POWER(E15,$B$3-1),0) -> 0 | G15: =ROUND(C15*POWER(E15,$B$3-1),0) -> 512000 | H15: =ROUND(D15*POWER(E15,$B$3-1),0) -> 256000 | I15: =F15*Parametres!$B$10+G15*Parametres!$B$11+H15*Parametres!$B$12 -> 1536000
A16: Optiques de visée / Targeting Optics | B16: 200 | C16: 100 | D16: 0 | E16: 2 | F16: =ROUND(B16*POWER(E16,$B$3-1),0) -> 25600 | G16: =ROUND(C16*POWER(E16,$B$3-1),0) -> 12800 | H16: =ROUND(D16*POWER(E16,$B$3-1),0) -> 0 | I16: =F16*Parametres!$B$10+G16*Parametres!$B$11+H16*Parametres!$B$12 -> 44800
A17: Technologie EMP / EMP Tech | B17: 1000 | C17: 300 | D17: 100 | E17: 2 | F17: =ROUND(B17*POWER(E17,$B$3-1),0) -> 128000 | G17: =ROUND(C17*POWER(E17,$B$3-1),0) -> 38400 | H17: =ROUND(D17*POWER(E17,$B$3-1),0) -> 12800 | I17: =F17*Parametres!$B$10+G17*Parametres!$B$11+H17*Parametres!$B$12 -> 224000
... A20: Coalition scientifique / Research Coalition | B20: 240000 | C20: 400000 | D20: 160000 | E20: 2 | F20: =ROUND(B20*POWER(E20,$B$3-1),0) -> 30720000 | G20: =ROUND(C20*POWER(E20,$B$3-1),0) -> 51200000 | H20: =ROUND(D20*POWER(E20,$B$3-1),0) -> 20480000 | I20: =F20*Parametres!$B$10+G20*Parametres!$B$11+H20*Parametres!$B$12 -> 168960000
A22: Mégastructures (Graviton) : requiert 300 000 d'énergie instantanée (ferme à générateurs), pas de coût ressources. Débloque le Béhémoth.

Sheet Unites
A1: Unités — coûts, stats, épaves, expéditions
A3: Unité (FR) | B3: EN | C3: Acier | D3: Comp. | E3: Carb. | F3: Éq. acier | G3: Structure | H3: Bouclier | I3: Arme | J3: Vitesse | K3: Fret | L3: Conso | M3: Pts expé | N3: Épaves (éq.acier)
A4: Camion de ravitaillement | B4: Supply Truck | C4: 2000 | D4: 2000 | E4: 0 | F4: =C4*Parametres!$B$10+D4*Parametres!$B$11+E4*Parametres!$B$12 -> 5000 | G4: =C4+D4 -> 4000 | H4: 5 | I4: 5000 | J4: 5000 | K4: 10 | L4: 300 | M4: =ROUND(G4/200,0) -> 20 | N4: =(C4*Parametres!$B$10+D4*Parametres!$B$11)*Parametres!$B$7 -> 1500
A5: Convoi lourd | B5: Heavy Convoy | C5: 6000 | D5: 6000 | E5: 0 | F5: =C5*Parametres!$B$10+D5*Parametres!$B$11+E5*Parametres!$B$12 -> 15000 | G5: =C5+D5 -> 12000 | H5: 5 | I5: 7500 | J5: 25000 | K5: 50 | L5: 300 | M5: =ROUND(G5/200,0) -> 60 | N5: =(C5*Parametres!$B$10+D5*Parametres!$B$11)*Parametres!$B$7 -> 4500
A6: Buggy de reconnaissance | B6: Recon Buggy | C6: 3000 | D6: 1000 | E6: 0 | F6: =C6*Parametres!$B$10+D6*Parametres!$B$11+E6*Parametres!$B$12 -> 4500 | G6: =C6+D6 -> 4000 | H6: 50 | I6: 12500 | J6: 50 | K6: 20 | L6: 300 | M6: =ROUND(G6/200,0) -> 20 | N6: =(C6*Parametres!$B$10+D6*Parametres!$B$11)*Parametres!$B$7 -> 1350
A7: Char léger | B7: Light Tank | C7: 6000 | D7: 4000 | E7: 0 | F7: =C7*Parametres!$B$10+D7*Parametres!$B$11+E7*Parametres!$B$12 -> 12000 | G7: =C7+D7 -> 10000 | H7: 150 | I7: 10000 | J7: 100 | K7: 75 | L7: 300 | M7: =ROUND(G7/200,0) -> 50 | N7: =(C7*Parametres!$B$10+D7*Parametres!$B$11)*Parametres!$B$7 -> 3600
A8: Char de combat | B8: Battle Tank | C8: 20000 | D8: 7000 | E8: 2000 | F8: =C8*Parametres!$B$10+D8*Parametres!$B$11+E8*Parametres!$B$12 -> 36500 | G8: =C8+D8 -> 27000 | H8: 400 | I8: 15000 | J8: 800 | K8: 300 | L8: 300 | M8: =ROUND(G8/200,0) -> 135 | N8: =(C8*Parametres!$B$10+D8*Parametres!$B$11)*Parametres!$B$7 -> 9150
A9: Char lourd | B9: Heavy Tank | C9: 45000 | D9: 15000 | E9: 0 | F9: =C9*Parametres!$B$10+D9*Parametres!$B$11+E9*Parametres!$B$12 -> 67500 | G9: =C9+D9 -> 60000 | H9: 1000 | I9: 10000 | J9: 1500 | K9: 500 | L9: 300 | M9: =ROUND(G9/200,0) -> 300 | N9: =(C9*Parametres!$B$10+D9*Parametres!$B$11)*Parametres!$B$7 -> 20250
A10: Artillerie à roquettes | B10: Rocket Artillery | C10: 30000 | D10: 40000 | E10: 15000 | F10: =C10*Parametres!$B$10+D10*Parametres!$B$11+E10*Parametres!$B$12 -> 135000 | G10: =C10+D10 -> 70000 | H10: 700 | I10: 10000 | J10: 750 | K10: 250 | L10: 300 | M10: =ROUND(G10/200,0) -> 350 | N10: =(C10*Parametres!$B$10+D10*Parametres!$B$11)*Parametres!$B$7 -> 27000
A11: Obusier de siège | B11: Siege Howitzer | C11: 50000 | D11: 25000 | E11: 15000 | F11: =C11*Parametres!$B$10+D11*Parametres!$B$11+E11*Parametres!$B$12 -> 132500 | G11: =C11+D11 -> 75000 | H11: 1000 | I11: 4000 | J11: 500 | K11: 700 | L11: 300 | M11: =ROUND(G11/200,0) -> 375 | N11: =(C11*Parametres!$B$10+D11*Parametres!$B$11)*Parametres!$B$7 -> 26250
A12: Hélicoptère de combat | B12: Gunship | C12: 60000 | D12: 50000 | E12: 15000 | F12: =C12*Parametres!$B$10+D12*Parametres!$B$11+E12*Parametres!$B$12 -> 180000 | G12: =C12+D12 -> 110000 | H12: 2000 | I12: 5000 | J12: 2000 | K12: 1000 | L12: 300 | M12: =ROUND(G12/200,0) -> 550 | N12: =(C12*Parametres!$B$10+D12*Parametres!$B$11)*Parametres!$B$7 -> 40500
A13: Forteresse « Béhémoth » | B13: Behemoth | C13: 5000000 | D13: 4000000 | E13: 1000000 | F13: =C13*Parametres!$B$10+D13*Parametres!$B$11+E13*Parametres!$B$12 -> 14000000 | G13: =C13+D13 -> 9000000 | H13: 200000 | I13: 100 | J13: 1000000 | K13: 1 | L13: 300 | M13: =ROUND(G13/200,0) -> 45000 | N13: =(C13*Parametres!$B$10+D13*Parametres!$B$11)*Parametres!$B$7 -> 3300000
A14: Dépanneuse | B14: Salvage Rig | C14: 10000 | D14: 6000 | E14: 2000 | F14: =C14*Parametres!$B$10+D14*Parametres!$B$11+E14*Parametres!$B$12 -> 25000 | G14: =C14+D14 -> 16000 | H14: 1 | I14: 2000 | J14: 20000 | K14: 300 | L14: 300 | M14: =ROUND(G14/200,0) -> 80 | N14: =(C14*Parametres!$B$10+D14*Parametres!$B$11)*Parametres!$B$7 -> 5700
A15: Drone de reconnaissance | B15: Scout Drone | C15: 0 | D15: 1000 | E15: 0 | F15: =C15*Parametres!$B$10+D15*Parametres!$B$11+E15*Parametres!$B$12 -> 1500 | G15: =C15+D15 -> 1000 | H15: 0 | I15: 100000000 | K15: 1 | L15: 300 | M15: =ROUND(G15/200,0) -> 5 | N15: =(C15*Parametres!$B$10+D15*Parametres!$B$11)*Parametres!$B$7 -> 450
A16: Convoi pionnier | B16: Pioneer Convoy | C16: 10000 | D16: 20000 | E16: 10000 | F16: =C16*Parametres!$B$10+D16*Parametres!$B$11+E16*Parametres!$B$12 -> 70000 | G16: =C16+D16 -> 30000 | H16: 50 | I16: 2500 | J16: 7500 | K16: 1000 | L16: 300 | M16: =ROUND(G16/200,0) -> 150 | N16: =(C16*Parametres!$B$10+D16*Parametres!$B$11)*Parametres!$B$7 -> 12000
A17: Escouade de rangers | B17: Ranger Squad | C17: 8000 | D17: 15000 | E17: 8000 | F17: =C17*Parametres!$B$10+D17*Parametres!$B$11+E17*Parametres!$B$12 -> 54500 | G17: =C17+D17 -> 23000 | H17: 200 | I17: 12000 | J17: 10000 | K17: 300 | L17: 300 | M17: =ROUND(G17/200,0) -> 115 | N17: =(C17*Parametres!$B$10+D17*Parametres!$B$11)*Parametres!$B$7 -> 9150
A19: Stats = OGame transposé (structure = acier+comp. ; le carburant ne génère pas d'épaves). Fret du drone lié à Parametres. Vitesses avant bonus de moteurs.
A21: RAPID FIRE — valeurs OGame v7 indicatives, bleu = modifiable
A22: Attaquant → Cible | B22: RF
A23: Char de combat → Buggy | B23: 6
A24: Char de combat → Nid de mitrailleuses | B24: 10
A25: Artillerie roquettes → Camion / Convoi lourd | B25: 3
A26: Artillerie roquettes → Char léger | B26: 4
A27: Artillerie roquettes → Char de combat | B27: 4
A28: Artillerie roquettes → Char lourd | B28: 7
A29: Obusier → Nid de mitrailleuses | B29: 20
A30: Obusier → Canon AA | B30: 20
A31: Obusier → Batterie AA lourde | B31: 10
A32: Hélico → Canon AA | B32: 10
A33: Hélico → Artillerie roquettes | B33: 2
A34: Toutes → Drone / Générateur | B34: 5
A35: Béhémoth → presque tout | B35: 30

Sheet Defenses
A1: Défenses & missiles
A3: Défense (FR) | B3: EN | C3: Acier | D3: Comp. | E3: Carb. | F3: Éq. acier | G3: Structure | H3: Bouclier | I3: Arme
A4: Nid de mitrailleuses | B4: MG Nest | C4: 2000 | D4: 0 | E4: 0 | F4: =C4*Parametres!$B$10+D4*Parametres!$B$11+E4*Parametres!$B$12 -> 2000 | G4: =C4+D4 -> 2000 | H4: 20 | I4: 80
A5: Canon anti-aérien | B5: AA Gun | C5: 1500 | D5: 500 | E5: 0 | F5: =C5*Parametres!$B$10+D5*Parametres!$B$11+E5*Parametres!$B$12 -> 2250 | G5: =C5+D5 -> 2000 | H5: 25 | I5: 100
A6: Batterie AA lourde | B6: Heavy AA Battery | C6: 6000 | D6: 2000 | E6: 0 | F6: =C6*Parametres!$B$10+D6*Parametres!$B$11+E6*Parametres!$B$12 -> 9000 | G6: =C6+D6 -> 8000 | H6: 100 | I6: 250
A7: Tour EMP | B7: EMP Tower | C7: 5000 | D7: 3000 | E7: 0 | F7: =C7*Parametres!$B$10+D7*Parametres!$B$11+E7*Parametres!$B$12 -> 9500 | G7: =C7+D7 -> 8000 | H7: 500 | I7: 150
A8: Casemate à canon électrique | B8: Railgun Emplacement | C8: 20000 | D8: 15000 | E8: 2000 | F8: =C8*Parametres!$B$10+D8*Parametres!$B$11+E8*Parametres!$B$12 -> 48500 | G8: =C8+D8 -> 35000 | H8: 200 | I8: 1100
A9: Canon lourd « Bastion » | B9: Heavy Cannon Bastion | C9: 50000 | D9: 50000 | E9: 30000 | F9: =C9*Parametres!$B$10+D9*Parametres!$B$11+E9*Parametres!$B$12 -> 215000 | G9: =C9+D9 -> 100000 | H9: 300 | I9: 3000
A10: Générateur de bouclier | B10: Shield Generator | C10: 10000 | D10: 10000 | E10: 0 | F10: =C10*Parametres!$B$10+D10*Parametres!$B$11+E10*Parametres!$B$12 -> 25000 | G10: =C10+D10 -> 20000 | H10: 2000 | I10: 1
A11: Bouclier de forteresse | B11: Fortress Shield | C11: 50000 | D11: 50000 | E11: 0 | F11: =C11*Parametres!$B$10+D11*Parametres!$B$11+E11*Parametres!$B$12 -> 125000 | G11: =C11+D11 -> 100000 | H11: 10000 | I11: 1
A12: Missile intercepteur | B12: Interceptor Missile | C12: 8000 | D12: 0 | E12: 2000 | F12: =C12*Parametres!$B$10+D12*Parametres!$B$11+E12*Parametres!$B$12 -> 14000 | G12: =C12+D12 -> 8000 | H12: 1 | I12: 1
A13: Missile balistique | B13: Ballistic Missile | C13: 12500 | D13: 2500 | E13: 10000 | F13: =C13*Parametres!$B$10+D13*Parametres!$B$11+E13*Parametres!$B$12 -> 46250 | G13: =C13+D13 -> 15000 | H13: 1 | I13: 12000
A15: Règles : ~70 % de reconstruction après combat (85 % avec Ingénieur) ; 0 % si détruit par missile balistique.
A16: La défense ne génère pas d'épaves (paramètre serveur). 1 seule coupole de chaque par base. Le missile balistique ignore les boucliers.
A17: Garde-fou drones : toute défense/unité posée détruit les drones en attaque — le Canon AA est accessible tôt.

Sheet Simulateur
A1: Simulateurs (temps de vol, raid, construction)
A3: 1. TEMPS DE VOL & CARBURANT
A4: Écart de zones (même secteur) | B4: 5
A5: Écart de secteurs (0 si même secteur) | B5: 0
A6: Vitesse de l'unité la plus lente | B6: 10000
A7: % de vitesse choisi (10-100) | B7: 100
A8: Nb de véhicules | B8: 50
A9: Conso de base / véhicule | B9: 300
A11: Distance (formule OGame) | B11: =IF(B5>0,2700+95*B5,1000+5*B4) -> 1025
A12: Temps de vol aller (min) | B12: =(10+35000/B7*SQRT(10*B11/B6))/Parametres!$B$5/60 -> 3.0362333
A13: Carburant aller-retour | B13: =2*ROUND(B8*B9*B11/35000*POWER(B7/100+1,2),0) -> 3514
A16: 2. RENTABILITÉ D'UN RAID
A17: Acier posé chez la cible | B17: 400000
A18: Composants posés | B18: 200000
A19: Carburant posé | B19: 100000
A20: Cible inactive ? (1=oui, 0=non) | B20: 1
A22: Taux de pillage appliqué | B22: =IF(B20=1,Parametres!$B$9,Parametres!$B$8) -> 0.75
A23: Butin total (unités de ressources) | B23: =ROUND((B17+B18+B19)*B22,0) -> 525000
A24: Butin en équivalent acier | B24: =ROUND((B17*Parametres!$B$10+B18*Parametres!$B$11+B19*Parametres!$B$12)*B22,0) -> 750000
A25: Camions nécessaires (fret 5 000) | B25: =ROUNDUP(B23/5000,0) -> 105
A26: Convois lourds nécessaires (fret 25 000) | B26: =ROUNDUP(B23/25000,0) -> 21
A27: Profit net éq. acier (butin − carburant du vol) | B27: =B24-B13*Parametres!$B$12 -> 739458
A30: 3. TEMPS DE CONSTRUCTION
A31: Coût Acier de l'objet | B31: 60000
A32: Coût Composants de l'objet | B32: 15000
A33: Niveau Corps du génie | B33: 8
A34: Niveau Chantier automatisé | B34: 0
A35: Niveau Usine de véhicules (unités) | B35: 6
A36: Niveau Centre de recherche (technos) | B36: 8
A38: Temps bâtiment (h) | B38: =(B31+B32)/(Parametres!$B$21*(1+B33)*Parametres!$B$4*POWER(2,B34)) -> 0.83333333
A39: Temps unité (h) | B39: =(B31+B32)/(Parametres!$B$21*(1+B35)*Parametres!$B$4*POWER(2,B34)) -> 1.0714286
A40: Temps recherche (h) | B40: =(B31+B32)/(Parametres!$B$22*(1+B36))/Parametres!$B$6 -> 2.0833333
